geekery/__init__.py
geekery-0.1.0.dist-info/METADATA
geekery-0.1.0.dist-info/WHEEL
geekery-0.1.0.dist-info/top_level.txt
geekery-0.1.0.dist-info/RECORD
