Metadata-Version: 2.2
Name: geekery
Version: 0.1.0
Summary: A minimal example package for PyPI
Author-email: Your Name <your.email@example.com>
Project-URL: Homepage, https://github.com/yourusername/geekery
Project-URL: Bug Tracker, https://github.com/yourusername/geekery/issues
